LICENSE
MANIFEST.in
README.md
requirements.txt
setup.py
torch_parameter_groups/__init__.py
torch_parameter_groups/__version__.py
torch_parameter_groups/group_parameters.py
torch_parameter_groups/group_rule.py
torch_parameter_groups/optimizer_factory.py
torch_parameter_groups.egg-info/PKG-INFO
torch_parameter_groups.egg-info/SOURCES.txt
torch_parameter_groups.egg-info/dependency_links.txt
torch_parameter_groups.egg-info/requires.txt
torch_parameter_groups.egg-info/top_level.txt
torch_parameter_groups/configs/__init__.py
torch_parameter_groups/configs/build/__init__.py
torch_parameter_groups/configs/build/group_rule_config.py
torch_parameter_groups/configs/build/optimizer_config.py
torch_parameter_groups/schema/group_rule_config.json
torch_parameter_groups/schema/optimizer_config.json