Metadata-Version: 2.1
Name: torch-parameter-groups
Version: 0.0.5.post1
Summary: Group PyTorch Parameters according to Rules
Home-page: https://github.com/FebruaryBreeze/torch-parameter-groups
Author: SF-Zhou
Author-email: sfzhou.scut@gmail.com
License: MIT
Keywords: PyTorch Parameter Groups
Platform: UNKNOWN
Requires-Python: >=3.6.0
